{
  "studyId": "PACA-AU",
  "analysisType": {
    "name": "composerSchema"
  },
  "samples": [
    {
      "submitterSampleId": "SP744311",
      "sampleType": "Total DNA",
      "matchedNormalSubmitterSampleId": "SP744301",
      "specimen": {
        "submitterSpecimenId": "SP744311",
        "specimenType": "Primary tumour - additional new primary",
        "tumourNormalDesignation": "Tumour",
        "specimenTissueSource": "Blood derived"
      },
      "donor": {
        "submitterDonorId": "DO7443",
        "gender": "Male"
      }
    }
  ],
  "files": [
    {
      "dataType": "Raw SV Calls",
      "fileName": "SP744311.snv.vcf.gz",
      "fileSize": 17248,
      "fileMd5sum": "67c16575dbd67ce0537f942096db9989",
      "fileAccess": "controlled",
      "fileType": "VCF",
      "info": {
        "dataCategory": "Simple Nucelotide Variation",
        "jbrowseCoordinates": "hg38:chr1:100000-200000"
      }
    },
    {
      "dataType": "Raw SV Calls",
      "fileName": "SP744311.snv.vcf.gz.tbi",
      "fileSize": 147,
      "fileMd5sum": "491a84762227efaf1e52637d25e69a17",
      "fileAccess": "controlled",
      "fileType": "TBI",
      "info": {
        "dataCategory": "Simple Nucelotide Variation",
        "jbrowseCoordinates": "hg38:chr1:100000-200000"
      }
    }
  ],
  "specimen": {
    "submitterPrimaryDiagnosisId": "PD744301",
    "submitterSpecimenId": "SP744301",
    "specimenAnatomicLocation": "C33",
    "tumourGradingSystem": "Nuclear grading system for DCIS",
    "tumourGrade": "GX"
  },
  "donor": {
    "submitterDonorId": "DO7443",
    "primarySite": [
      "Hematopoietic and reticuloendothelial systems"
    ],
    "vitalStatus": "Alive",
    "survivalTime": null,
    "causeOfDeath": null,
    "primaryDiagnosis": [
      {
        "submitterPrimaryDiagnosisId": "PD744301",
        "ageAtDiagnosis": 57,
        "cancerTypeCode": "C88.3",
        "clinicalTumourStagingSystem": "AJCC 7th edition",
        "clinicalStageGroup": "Stage IIC",
        "treatment": [
          {
            "submitterTreatmentId": "TR744301",
            "treatmentType": [
              "Chemotherapy"
            ],
            "treatmentStartInterval": 21,
            "treatmentDuration": 70,
            "responseToTreatment": "Disease progression",
            "chemotherapy": [
              {
                "drugName": [
                  "Azacitidine"
                ]
              }
            ]
          }
        ],
        "followUp": [
          {
            "submitterFollowUpId": "FO744301",
            "submitterTreatmentId": "TR744301",
            "intervalOfFollowUp": 67,
            "diseaseStatusAtFollowUp": "Complete remission",
            "relapseType": null
          }
        ]
      }
    ]
  },
  "experiment": {
    "platform": "ONT",
    "experimentalStrategy": "WGS",
    "model": "PromethION",
    "sequencingCenter": "GATC",
    "sequencingDate": "2022-12-12T19:00:00.000Z"
  },
  "workflow": {
    "workflowName": "Sanger Variant Calling",
    "workflowShortName": "SangerVariant",
    "workflowVersion": "0.9.8",
    "genomeBuild": "GRCh38_hla_decoy_ebv",
    "inputs": [
      {
        "analysisType": "sequencing_alignment",
        "tumourAnalysisId": "00000000-0000-0000-0000-0000000007443",
        "normalAnalysisId": "00000000-0000-0000-0000-0000000007443"
      }
    ],
    "runId": "RI7443",
    "sessionId": "SI7443"
  },
  "publication": {
    "publication": "Nature",
    "doi": "10.1038/s41591-023-02650-10"
  }
}
