{"object_id": "4fd0be6f-ce25-521a-9a54-1dbc2318ce05", "study_id": "demo", "data_type": "Raw InDel Calls", "file_type": "VCF", "file_access": "open", "analysis": {"analysis_id": "22286e7c-85f7-4aec-a86e-7c85f7eaecb2", "analysis_type": "quickStartSchema", "analysis_version": 1, "analysis_state": "PUBLISHED", "updated_at": 1720110341824, "first_published_at": 1720110341809, "published_at": 1720110341809, "experiment": {"model": "SEQUEL IIe", "platform": "PacBio", "sequencingDate": "2021-03-08T19:00:00.000Z", "sequencingCenter": "CGTA", "experimentalStrategy": "WXS"}, "analysisStateHistory": [{"initialState": "UNPUBLISHED", "updatedState": "PUBLISHED", "updatedAt": "2024-07-04T16:25:41.809441"}], "collaborator": [{"name": "MICR", "contactEmail": "susannorton@micr.ca"}], "createdAt": "2024-07-04T16:19:21.844701", "donor": {"primarySite": "Bronchus and lung", "vitalStatus": "Deceased", "causeOfDeath": "Died of other reasons", "survivalTime": 439, "primaryDiagnosis": [{"followUp": [{"relapseType": null, "intervalOfFollowUp": 50, "submitterFollowUpId": "FO011501", "submitterTreatmentId": "TR011501", "diseaseStatusAtFollowUp": "Partial remission"}], "treatment": [{"chemotherapy": [{"drugName": "Azacitidine "}], "treatmentType": ["Chemotherapy"], "treatmentDuration": 34, "responseToTreatment": "Minor response", "submitterTreatmentId": "TR011501", "treatmentStartInterval": 79}], "ageAtDiagnosis": 36, "cancerTypeCode": "C34.3", "clinicalStageGroup": "Stage III", "clinicalTumourStagingSystem": "AJCC 6th edition", "submitterPrimaryDiagnosisId": "PD011501"}, {"followUp": [{"relapseType": null, "intervalOfFollowUp": 33, "submitterFollowUpId": "FO011502", "submitterTreatmentId": "TR011502", "diseaseStatusAtFollowUp": "Relapse or recurrence"}], "treatment": [{"radiation": [{"anatomicalSiteIrradiated": "Body", "radiationTherapyModality": "Photon"}], "chemotherapy": [{"drugName": "Paclitaxel "}], "treatmentType": ["Chemotherapy", "Radiation therapy"], "treatmentDuration": 56, "responseToTreatment": "Complete response", "submitterTreatmentId": "TR011502", "treatmentStartInterval": 70}], "ageAtDiagnosis": 1, "cancerTypeCode": "C34.2", "clinicalStageGroup": "Stage IB", "clinicalTumourStagingSystem": "FIGO staging system", "submitterPrimaryDiagnosisId": "PD011502"}], "submitterDonorId": "DO0115"}, "publication": {"doi": "10.1093/nar/gkae188", "publication": "NAR"}, "specimen": {"tumourGrade": "G3", "submitterSpecimenId": "SP011501", "tumourGradingSystem": "Three-tier grading system", "specimenAnatomicLocation": "C14", "submitterPrimaryDiagnosisId": "PD011501"}, "workflow": {"runId": "RI0115", "inputs": [{"analysisType": "sequencing_alignment", "normalAnalysisId": "00000000-0000-0000-0000-0000000000115", "tumourAnalysisId": "00000000-0000-0000-0000-0000000000115"}], "sessionId": "SI0115", "genomeBuild": "GRCh38_hla_decoy_ebv", "workflowName": "Sanger Variant Calling", "workflowVersion": "0.9.8", "workflowShortName": "SangerVariant"}}, "file": {"name": "SP011511.indel.vcf.gz", "md5sum": "c445d6cd5e1aa1d7dec13096feae788c", "size": 17328, "data_type": "Raw InDel Calls", "index_file": {"object_id": "deaeaa56-c56d-54ee-ad75-f5b90bb7eda6", "name": "SP011511.indel.vcf.gz.tbi", "file_type": "TBI", "md5sum": "ae025b596b2fb562d33073338eb23a7d", "data_type": "Raw InDel Calls", "size": 148, "dataCategory": "Simple Nucelotide Variation", "jbrowseCoordinates": "hg38:chr1:100000-200000"}, "dataCategory": "Simple Nucelotide Variation", "jbrowseCoordinates": "hg38:chr1:100000-200000"}, "repositories": [{"code": "song.overture", "organization": "Overture", "name": "Overture", "type": "S3", "country": "CA", "url": "http://song:8080"}], "donors": [{"donor_id": "1a0cc916-465c-5b06-8eb7-c4fa438e496f", "submitter_donor_id": "DO0115", "gender": "Female", "specimens": [{"specimen_id": "89e3e128-6d1a-55cc-aae3-e62f5e2d4bdc", "specimen_type": "Primary tumour - adjacent to normal", "submitter_specimen_id": "SP011511", "samples": [{"sample_id": "89e3e128-6d1a-55cc-aae3-e62f5e2d4bdc", "submitter_sample_id": "SP011511", "sample_type": "Total DNA", "matched_normal_submitter_sample_id": "SP011501"}], "tumour_normal_designation": "Tumour", "specimen_tissue_source": "Blood derived - bone marrow"}]}], "dataCategory": "Simple Nucelotide Variation", "jbrowseCoordinates": "hg38:chr1:100000-200000"}