{
  "studyId": "AICR",
  "analysisType": {
    "name": "quickStartSchema"
  },
  "samples": [
    {
      "submitterSampleId": "SP933301",
      "sampleType": "Total DNA",
      "matchedNormalSubmitterSampleId": null,
      "specimen": {
        "submitterSpecimenId": "SP933301",
        "specimenType": "Normal",
        "tumourNormalDesignation": "Normal",
        "specimenTissueSource": "Blood derived - bone marrow"
      },
      "donor": {
        "submitterDonorId": "DO9333",
        "gender": "Other"
      }
    }
  ],
  "files": [
    {
      "dataType": "Raw SV Calls",
      "fileName": "SP933301.snv.vcf.gz",
      "fileSize": 17248,
      "fileMd5sum": "b1f642c5cdf743b068379a03939a2512",
      "fileAccess": "controlled",
      "fileType": "VCF",
      "info": {
        "dataCategory": "Simple Nucelotide Variation",
        "jbrowseCoordinates": "hg38:chr1:100000-200000"
      }
    },
    {
      "dataType": "Raw SV Calls",
      "fileName": "SP933301.snv.vcf.gz.tbi",
      "fileSize": 148,
      "fileMd5sum": "75f26b946ad64977b1148f08f33a26b3",
      "fileAccess": "controlled",
      "fileType": "TBI",
      "info": {
        "dataCategory": "Simple Nucelotide Variation",
        "jbrowseCoordinates": "hg38:chr1:100000-200000"
      }
    }
  ],
  "specimen": {
    "submitterPrimaryDiagnosisId": "PD933301",
    "submitterSpecimenId": "SP933301",
    "specimenAnatomicLocation": "C55",
    "tumourGradingSystem": "Grading system for GNETs",
    "tumourGrade": "G1"
  },
  "donor": {
    "submitterDonorId": "DO9333",
    "primarySite": [
      "Brain"
    ],
    "vitalStatus": "Alive",
    "survivalTime": null,
    "causeOfDeath": null,
    "primaryDiagnosis": [
      {
        "submitterPrimaryDiagnosisId": "PD933301",
        "ageAtDiagnosis": 30,
        "cancerTypeCode": "C71.6",
        "clinicalTumourStagingSystem": "Rai staging system",
        "clinicalStageGroup": "Stage I",
        "treatment": [
          {
            "submitterTreatmentId": "TR933301",
            "treatmentType": [
              "Chemotherapy",
              "Hormonal therapy"
            ],
            "treatmentStartInterval": 57,
            "treatmentDuration": 59,
            "responseToTreatment": "Complete response",
            "chemotherapy": [
              {
                "drugName": [
                  "Azacitidine"
                ]
              }
            ],
            "hormoneTherapy": [
              {
                "drugName": [
                  "Exemestane"
                ]
              }
            ]
          }
        ],
        "followUp": [
          {
            "submitterFollowUpId": "FO933301",
            "submitterTreatmentId": "TR933301",
            "intervalOfFollowUp": 5,
            "diseaseStatusAtFollowUp": "Stable",
            "relapseType": null
          }
        ]
      }
    ]
  },
  "experiment": {
    "platform": "PacBio",
    "experimentalStrategy": "WXS",
    "model": "SEQUEL IIe",
    "sequencingCenter": "CGTA",
    "sequencingDate": "2021-03-08T19:00:00.000Z"
  },
  "workflow": {
    "workflowName": "Sanger Variant Calling",
    "workflowShortName": "SangerVariant",
    "workflowVersion": "0.9.8",
    "genomeBuild": "GRCh38_hla_decoy_ebv",
    "inputs": [
      {
        "analysisType": "sequencing_alignment",
        "tumourAnalysisId": "00000000-0000-0000-0000-0000000009333",
        "normalAnalysisId": "00000000-0000-0000-0000-0000000009333"
      }
    ],
    "runId": "RI9333",
    "sessionId": "SI9333"
  },
  "publication": {
    "publication": "NAR",
    "doi": "10.1093/nar/gkae188"
  }
}
